{
    "ipcMode": null,
    "executionRoleArn": "arn:aws:iam::747391415460:role/ecsTaskExecutionRole",
    "containerDefinitions": [
        {
            "dnsSearchDomains": null,
            "environmentFiles": null,
            "logConfiguration": null,
            "entryPoint": null,
            "portMappings": [
                {
                    "hostPort": 0,
                    "protocol": "tcp",
                    "containerPort": 32262
                },
                {
                    "hostPort": 0,
                    "protocol": "udp",
                    "containerPort": 32263
                },
                {
                    "hostPort": 0,
                    "protocol": "tcp",
                    "containerPort": 32273
                }
            ],
            "command": null,
            "linuxParameters": {
                "capabilities": {
                    "add": [
                        "SETPCAP",
                        "MKNOD",
                        "AUDIT_WRITE",
                        "CHOWN",
                        "NET_RAW",
                        "DAC_OVERRIDE",
                        "FOWNER",
                        "FSETID",
                        "KILL",
                        "SETGID",
                        "SETUID",
                        "NET_BIND_SERVICE",
                        "SYS_CHROOT",
                        "SETFCAP"
                    ],
                    "drop": ["ALL"]
                },
                "sharedMemorySize": 2048,
                "tmpfs": [
                    {
                        "mountOptions": null,
                        "containerPath": "/run",
                        "size": 50
                    },
                    {
                        "mountOptions": null,
                        "containerPath": "/run/lock",
                        "size": 50
                    }
                ],
                "devices": null,
                "maxSwap": null,
                "swappiness": null,
                "initProcessEnabled": null
            },
            "cpu": 0,
            "environment": [
                {
                    "name": "NVIDIA_DRIVER_CAPABILITIES",
                    "value": "all"
                },
                {
                    "name": "NVIDIA_VISIBLE_DEVICES",
                    "value": "all"
                }
            ],
            "resourceRequirements": null,
            "ulimits": null,
            "dnsServers": null,
            "mountPoints": [
                {
                    "readOnly": true,
                    "containerPath": "/sys/fs/cgroup",
                    "sourceVolume": "cgroup"
                },
                {
                    "readOnly": true,
                    "containerPath": "/fractal",
                    "sourceVolume": "fractal"
                }
            ],
            "workingDirectory": null,
            "secrets": null,
            "dockerSecurityOptions": [],
            "memory": 6144,
            "memoryReservation": null,
            "volumesFrom": [],
            "stopTimeout": null,
            "image": "[IMAGE-PLACEHOLDER]",
            "startTimeout": null,
            "firelensConfiguration": null,
            "dependsOn": null,
            "disableNetworking": null,
            "interactive": null,
            "healthCheck": null,
            "essential": true,
            "links": null,
            "hostname": null,
            "extraHosts": null,
            "pseudoTerminal": null,
            "user": null,
            "readonlyRootFilesystem": null,
            "dockerLabels": null,
            "systemControls": null,
            "privileged": null,
            "name": "fractal-container"
        }
    ],
    "memory": null,
    "taskRoleArn": "arn:aws:iam::747391415460:role/ecsTaskExecutionRole",
    "family": "fractal-browsers-firefox",
    "pidMode": null,
    "requiresCompatibilities": ["EC2"],
    "networkMode": "bridge",
    "cpu": null,
    "inferenceAccelerators": [],
    "proxyConfiguration": null,
    "volumes": [
        {
            "efsVolumeConfiguration": null,
            "name": "cgroup",
            "host": {
                "sourcePath": "/sys/fs/cgroup"
            },
            "dockerVolumeConfiguration": null
        },
        {
            "efsVolumeConfiguration": null,
            "name": "fractal",
            "host": {
                "sourcePath": "/fractal"
            },
            "dockerVolumeConfiguration": null
        }
    ],
    "placementConstraints": [],
    "tags": []
}
